fetch.py
metrics.py
pricing.py
rds_viewer.py
reserved_instances.py
ui.py
docs/BENCHMARKING.md
docs/HOMEBREW.md
docs/IMPROVEMENTS-1.md
docs/PRE-COMMIT-HOOK.md
docs/RESERVED-INSTANCES.md
docs/image-help.png
docs/image.png
smart_rds_viewer-1.0.0.dist-info/METADATA
smart_rds_viewer-1.0.0.dist-info/WHEEL
smart_rds_viewer-1.0.0.dist-info/entry_points.txt
smart_rds_viewer-1.0.0.dist-info/top_level.txt
smart_rds_viewer-1.0.0.dist-info/RECORD
