Metadata-Version: 2.4
Name: smart-rds-viewer
Version: 1.0.0
Summary: Your terminal companion for monitoring Amazon RDS instances with real-time data, pricing, and interactive insights!
Author-email: Smart RDS Viewer <smart.rds.viewer@example.com>
Maintainer-email: Smart RDS Viewer <smart.rds.viewer@example.com>
License: MIT
Project-URL: Homepage, https://github.com/yourusername/smart-rds-viewer
Project-URL: Repository, https://github.com/yourusername/smart-rds-viewer
Project-URL: Documentation, https://github.com/yourusername/smart-rds-viewer#readme
Project-URL: Bug Reports, https://github.com/yourusername/smart-rds-viewer/issues
Keywords: aws,rds,monitoring,cloudwatch,pricing,terminal,cli
Classifier: Development Status :: 4 - Beta
Classifier: Intended Audience :: Developers
Classifier: Intended Audience :: System Administrators
Classifier: Topic :: System :: Monitoring
Classifier: Topic :: System :: Systems Administration
Classifier: Topic :: Utilities
Classifier: License :: OSI Approved :: MIT License
Classifier: Programming Language :: Python :: 3
Classifier: Programming Language :: Python :: 3.8
Classifier: Programming Language :: Python :: 3.9
Classifier: Programming Language :: Python :: 3.10
Classifier: Programming Language :: Python :: 3.11
Classifier: Programming Language :: Python :: 3.12
Classifier: Operating System :: OS Independent
Classifier: Environment :: Console
Classifier: Environment :: Console :: Curses
Requires-Python: >=3.8
Requires-Dist: boto3
Requires-Dist: rich
Requires-Dist: typer
Requires-Dist: readchar
